travelscheduler/Vasttrafik.py
travelscheduler/__init__.py
travelscheduler-1.0.dist-info/METADATA
travelscheduler-1.0.dist-info/WHEEL
travelscheduler-1.0.dist-info/top_level.txt
travelscheduler-1.0.dist-info/RECORD
